korrektor_py/__init__.py
korrektor_py/api.py
korrektor_py/core.py
korrektor_py/exceptions.py
korrektor_py/models.py
korrektor_py/utils.py
korrektor_py-1.0.0.dist-info/LICENSE
korrektor_py-1.0.0.dist-info/METADATA
korrektor_py-1.0.0.dist-info/WHEEL
korrektor_py-1.0.0.dist-info/top_level.txt
korrektor_py-1.0.0.dist-info/RECORD
