Metadata-Version: 2.1
Name: korrektor-py
Version: 1.0.0
Summary: Python wrapper for the https://korrektor.uz/api
Home-page: https://github.com/AbduazizZiyodov/korrektor-py
Author: Abduaziz Ziyodov
Author-email: abduaziz.ziyodov@mail.ru
License: MIT
Platform: any
Classifier: License :: OSI Approved :: MIT License
Classifier: Operating System :: OS Independent
Classifier: Programming Language :: Python :: 3
Classifier: Programming Language :: Python :: 3.8
Classifier: Programming Language :: Python :: Implementation :: CPython
Requires-Python: >=3.8
Requires-Dist: httpx
Requires-Dist: pydantic
Requires-Dist: pytest
